pyi_mcp/__init__.py
pyi_mcp/server.py
pyi_mcp-0.0.2.dist-info/licenses/LICENSE
pyi_mcp-0.0.2.dist-info/METADATA
pyi_mcp-0.0.2.dist-info/WHEEL
pyi_mcp-0.0.2.dist-info/entry_points.txt
pyi_mcp-0.0.2.dist-info/top_level.txt
pyi_mcp-0.0.2.dist-info/RECORD
