Metadata-Version: 2.4
Name: pyi-mcp
Version: 0.0.2
Summary: PYI-MCP
Author-email: lxwang12 <lxwang12@iflytek.com>
License: MIT
Classifier: Programming Language :: Python :: 3
Classifier: License :: OSI Approved :: MIT License
Classifier: Operating System :: OS Independent
Requires-Python: >=3.10
License-File: LICENSE
Requires-Dist: mcp[cli]>=1.3.0
Requires-Dist: requests
Dynamic: license-file
